versiontag/__init__.py
versiontag/tests/__init__.py
versiontag/tests/test_versiontag.py
versiontag/tests/utils.py
versiontag-1.2.0.dist-info/DESCRIPTION.rst
versiontag-1.2.0.dist-info/METADATA
versiontag-1.2.0.dist-info/RECORD
versiontag-1.2.0.dist-info/WHEEL
versiontag-1.2.0.dist-info/metadata.json
versiontag-1.2.0.dist-info/top_level.txt
